{
  "schemaVersion": "1",
  "thresholdsVersion": "capture-quality-thresholds-v1",
  "sampleFrames": 8,
  "maxBlackFrameRatio": 0.1,
  "maxBlankFrameRatio": 0.1,
  "warnFrozenPairRatio": 0.6,
  "maxFrozenPairRatio": 0.8,
  "minimumEdgeDensity": 0.002,
  "minimumEffectiveUiTextPx": 12,
  "captionMaxLines": 3,
  "captionMinimumMarginPx": 64,
  "captionMinimumUiGapPx": 120,
  "pointerMoveMinimumMs": 200,
  "pointerMoveMaximumMs": 1000,
  "typingDelayMinimumMs": 15,
  "typingDelayMaximumMs": 80,
  "afterActionMinimumMs": 500,
  "afterActionMaximumMs": 2500,
  "cueMinimumMs": 750,
  "cueMaximumMs": 6000,
  "stepPacingMinimumMs": 750,
  "stepPacingMaximumMs": 15000,
  "maximumPanCropWidthsPerSecond": 2
}
